[{"startIP":"2750021632","endIP":"2750087167","countryCode":"US","countryName":"United States"},{"startIP":"2750087168","endIP":"2750218239","countryCode":"US","countryName":"United States"},{"startIP":"2750218240","endIP":"2750283775","countryCode":"US","countryName":"United States"},{"startIP":"2750283776","endIP":"2750349311","countryCode":"US","countryName":"United States"},{"startIP":"2750349312","endIP":"2750414847","countryCode":"KR","countryName":"South Korea"},{"startIP":"2750414848","endIP":"2750480383","countryCode":"US","countryName":"United States"},{"startIP":"2750480384","endIP":"2750545919","countryCode":"US","countryName":"United States"},{"startIP":"2750545920","endIP":"2750611455","countryCode":"DE","countryName":"Germany"},{"startIP":"2750611456","endIP":"2750676991","countryCode":"US","countryName":"United States"},{"startIP":"2750676992","endIP":"2750742527","countryCode":"US","countryName":"United States"},{"startIP":"2750742528","endIP":"2750808063","countryCode":"US","countryName":"United States"},{"startIP":"2750808064","endIP":"2750873599","countryCode":"US","countryName":"United States"},{"startIP":"2750873600","endIP":"2750939135","countryCode":"CL","countryName":"Chile"},{"startIP":"2750939136","endIP":"2750971903","countryCode":"US","countryName":"United States"},{"startIP":"2750971904","endIP":"2751004671","countryCode":"US","countryName":"United States"},{"startIP":"2751004672","endIP":"2751070207","countryCode":"US","countryName":"United States"},{"startIP":"2751070208","endIP":"2751135743","countryCode":"CL","countryName":"Chile"},{"startIP":"2751135744","endIP":"2751201279","countryCode":"US","countryName":"United States"},{"startIP":"2751201280","endIP":"2751266815","countryCode":"US","countryName":"United States"},{"startIP":"2751266816","endIP":"2751332351","countryCode":"US","countryName":"United States"},{"startIP":"2751332352","endIP":"2751397887","countryCode":"US","countryName":"United States"},{"startIP":"2751397888","endIP":"2751463423","countryCode":"KR","countryName":"South Korea"},{"startIP":"2751463424","endIP":"2751528959","countryCode":"KZ","countryName":"Kazakhstan"},{"startIP":"2751528960","endIP":"2751594495","countryCode":"FR","countryName":"France"},{"startIP":"2751594496","endIP":"2751660031","countryCode":"FR","countryName":"France"},{"startIP":"2751660032","endIP":"2751725567","countryCode":"AT","countryName":"Austria"},{"startIP":"2751725568","endIP":"2751791103","countryCode":"SE","countryName":"Sweden"},{"startIP":"2751791104","endIP":"2751856639","countryCode":"FI","countryName":"Finland"},{"startIP":"2751856640","endIP":"2751922175","countryCode":"GB","countryName":"Great Britain (UK)"},{"startIP":"2751922176","endIP":"2751987711","countryCode":"FR","countryName":"France"},{"startIP":"2751987712","endIP":"2752053247","countryCode":"SI","countryName":"Slovenia"},{"startIP":"2752053248","endIP":"2752118783","countryCode":"SE","countryName":"Sweden"},{"startIP":"2752118784","endIP":"2752184319","countryCode":"SE","countryName":"Sweden"},{"startIP":"2752184320","endIP":"2752249855","countryCode":"GB","countryName":"Great Britain (UK)"},{"startIP":"2752249856","endIP":"2752315391","countryCode":"GB","countryName":"Great Britain (UK)"},{"startIP":"2752315392","endIP":"2752380927","countryCode":"FI","countryName":"Finland"},{"startIP":"2752380928","endIP":"2752446463","countryCode":"CH","countryName":"Switzerland"},{"startIP":"2752446464","endIP":"2752511999","countryCode":"BE","countryName":"Belgium"},{"startIP":"2752512000","endIP":"2753560575","countryCode":"DE","countryName":"Germany"},{"startIP":"2753560576","endIP":"2753691647","countryCode":"DE","countryName":"Germany"},{"startIP":"2753691648","endIP":"2753757183","countryCode":"DE","countryName":"Germany"},{"startIP":"2753757184","endIP":"2753822719","countryCode":"BE","countryName":"Belgium"},{"startIP":"2753822720","endIP":"2753888255","countryCode":"GB","countryName":"Great Britain (UK)"},{"startIP":"2753888256","endIP":"2753953791","countryCode":"SE","countryName":"Sweden"},{"startIP":"2753953792","endIP":"2754019327","countryCode":"GB","countryName":"Great Britain (UK)"},{"startIP":"2754019328","endIP":"2754084863","countryCode":"GB","countryName":"Great Britain (UK)"},{"startIP":"2754084864","endIP":"2754117631","countryCode":"KZ","countryName":"Kazakhstan"},{"startIP":"2754117632","endIP":"2754125823","countryCode":"NL","countryName":"Netherlands"},{"startIP":"2754125824","endIP":"2754127871","countryCode":"DE","countryName":"Germany"},{"startIP":"2754127872","endIP":"2754129919","countryCode":"SK","countryName":"Slovak Republic"},{"startIP":"2754129920","endIP":"2754131967","countryCode":"SE","countryName":"Sweden"},{"startIP":"2754131968","endIP":"2754134015","countryCode":"PL","countryName":"Poland"},{"startIP":"2754134016","endIP":"2754138111","countryCode":"DE","countryName":"Germany"},{"startIP":"2754138112","endIP":"2754142207","countryCode":"GB","countryName":"Great Britain (UK)"},{"startIP":"2754142208","endIP":"2754144255","countryCode":"BA","countryName":"Bosnia and Herzegovina"},{"startIP":"2754144256","endIP":"2754146303","countryCode":"DE","countryName":"Germany"},{"startIP":"2754146304","endIP":"2754148351","countryCode":"PL","countryName":"Poland"},{"startIP":"2754148352","endIP":"2754150399","countryCode":"MK","countryName":"Macedonia"},{"startIP":"2754150400","endIP":"2754215935","countryCode":"BR","countryName":"Brazil"},{"startIP":"2754215936","endIP":"2754281471","countryCode":"PR","countryName":"Puerto Rico"},{"startIP":"2754281472","endIP":"2754347007","countryCode":"JP","countryName":"Japan"},{"startIP":"2754347008","endIP":"2754412543","countryCode":"US","countryName":"United States"},{"startIP":"2754412544","endIP":"2754478079","countryCode":"US","countryName":"United States"},{"startIP":"2754478080","endIP":"2754543615","countryCode":"JP","countryName":"Japan"},{"startIP":"2754543616","endIP":"2754609151","countryCode":"US","countryName":"United States"},{"startIP":"2754609152","endIP":"2754674687","countryCode":"SE","countryName":"Sweden"},{"startIP":"2754674688","endIP":"2754740223","countryCode":"US","countryName":"United States"},{"startIP":"2754740224","endIP":"2754805759","countryCode":"US","countryName":"United States"},{"startIP":"2754805760","endIP":"2754871295","countryCode":"US","countryName":"United States"},{"startIP":"2754871296","endIP":"2754936831","countryCode":"US","countryName":"United States"},{"startIP":"2754936832","endIP":"2755002367","countryCode":"AU","countryName":"Australia"},{"startIP":"2755002368","endIP":"2755067903","countryCode":"US","countryName":"United States"},{"startIP":"2755067904","endIP":"2755133439","countryCode":"US","countryName":"United States"},{"startIP":"2755133440","endIP":"2755198975","countryCode":"US","countryName":"United States"},{"startIP":"2755198976","endIP":"2755264511","countryCode":"US","countryName":"United States"},{"startIP":"2755264512","endIP":"2755330047","countryCode":"US","countryName":"United States"},{"startIP":"2755330048","endIP":"2755395583","countryCode":"DE","countryName":"Germany"},{"startIP":"2755395584","endIP":"2755461119","countryCode":"FR","countryName":"France"},{"startIP":"2755461120","endIP":"2755526655","countryCode":"DE","countryName":"Germany"},{"startIP":"2755526656","endIP":"2755592191","countryCode":"US","countryName":"United States"},{"startIP":"2755592192","endIP":"2755657727","countryCode":"GB","countryName":"Great Britain (UK)"},{"startIP":"2755657728","endIP":"2755723263","countryCode":"US","countryName":"United States"},{"startIP":"2755723264","endIP":"2755788799","countryCode":"US","countryName":"United States"},{"startIP":"2755788800","endIP":"2755854335","countryCode":"US","countryName":"United States"},{"startIP":"2755854336","endIP":"2755919871","countryCode":"US","countryName":"United States"},{"startIP":"2755919872","endIP":"2755985407","countryCode":"US","countryName":"United States"},{"startIP":"2755985408","endIP":"2756050943","countryCode":"JP","countryName":"Japan"},{"startIP":"2756050944","endIP":"2756182015","countryCode":"JP","countryName":"Japan"},{"startIP":"2756182016","endIP":"2756247551","countryCode":"US","countryName":"United States"},{"startIP":"2756247552","endIP":"2756313087","countryCode":"UY","countryName":"Uruguay"},{"startIP":"2756313088","endIP":"2756378623","countryCode":"US","countryName":"United States"},{"startIP":"2756378624","endIP":"2756444159","countryCode":"AU","countryName":"Australia"},{"startIP":"2756444160","endIP":"2756509695","countryCode":"US","countryName":"United States"},{"startIP":"2756509696","endIP":"2756575231","countryCode":"CL","countryName":"Chile"},{"startIP":"2756575232","endIP":"2756640767","countryCode":"SG","countryName":"Singapore"},{"startIP":"2756640768","endIP":"2756706303","countryCode":"US","countryName":"United States"},{"startIP":"2756706304","endIP":"2756771839","countryCode":"AU","countryName":"Australia"},{"startIP":"2756771840","endIP":"2756837375","countryCode":"FR","countryName":"France"},{"startIP":"2756837376","endIP":"2756902911","countryCode":"US","countryName":"United States"},{"startIP":"2756902912","endIP":"2756968447","countryCode":"US","countryName":"United States"},{"startIP":"2756968448","endIP":"2757033983","countryCode":"US","countryName":"United States"},{"startIP":"2757033984","endIP":"2757099519","countryCode":"BR","countryName":"Brazil"},{"startIP":"2757099520","endIP":"2757165055","countryCode":"US","countryName":"United States"},{"startIP":"2757165056","endIP":"2757230591","countryCode":"US","countryName":"United States"},{"startIP":"2757230592","endIP":"2757296127","countryCode":"ZA","countryName":"South Africa"},{"startIP":"2757296128","endIP":"2757361663","countryCode":"US","countryName":"United States"},{"startIP":"2757361664","endIP":"2757427199","countryCode":"US","countryName":"United States"},{"startIP":"2757427200","endIP":"2757492735","countryCode":"US","countryName":"United States"},{"startIP":"2757492736","endIP":"2757558271","countryCode":"US","countryName":"United States"},{"startIP":"2757558272","endIP":"2757623807","countryCode":"US","countryName":"United States"},{"startIP":"2757623808","endIP":"2757689343","countryCode":"US","countryName":"United States"},{"startIP":"2757689344","endIP":"2757754879","countryCode":"US","countryName":"United States"},{"startIP":"2757754880","endIP":"2757820415","countryCode":"CL","countryName":"Chile"},{"startIP":"2757820416","endIP":"2757885951","countryCode":"AU","countryName":"Australia"},{"startIP":"2757885952","endIP":"2757951487","countryCode":"CL","countryName":"Chile"},{"startIP":"2757951488","endIP":"2758017023","countryCode":"US","countryName":"United States"},{"startIP":"2758017024","endIP":"2758082559","countryCode":"IN","countryName":"India"},{"startIP":"2758082560","endIP":"2758148095","countryCode":"US","countryName":"United States"},{"startIP":"2758148096","endIP":"2758213631","countryCode":"CA","countryName":"Canada"},{"startIP":"2758213632","endIP":"2758279167","countryCode":"US","countryName":"United States"},{"startIP":"2758279168","endIP":"2758344703","countryCode":"US","countryName":"United States"},{"startIP":"2758344704","endIP":"2758410239","countryCode":"US","countryName":"United States"},{"startIP":"2758410240","endIP":"2758475775","countryCode":"US","countryName":"United States"},{"startIP":"2758475776","endIP":"2758541311","countryCode":"US","countryName":"United States"},{"startIP":"2758541312","endIP":"2758606847","countryCode":"AU","countryName":"Australia"},{"startIP":"2758606848","endIP":"2758672383","countryCode":"US","countryName":"United States"},{"startIP":"2758672384","endIP":"2758737919","countryCode":"US","countryName":"United States"},{"startIP":"2758737920","endIP":"2758803455","countryCode":"US","countryName":"United States"},{"startIP":"2758803456","endIP":"2758868991","countryCode":"AU","countryName":"Australia"},{"startIP":"2758868992","endIP":"2758934527","countryCode":"US","countryName":"United States"},{"startIP":"2758934528","endIP":"2759000063","countryCode":"US","countryName":"United States"},{"startIP":"2759000064","endIP":"2759065599","countryCode":"TH","countryName":"Thailand"},{"startIP":"2759065600","endIP":"2759131135","countryCode":"US","countryName":"United States"},{"startIP":"2759131136","endIP":"2759196671","countryCode":"US","countryName":"United States"},{"startIP":"2759196672","endIP":"2759262207","countryCode":"US","countryName":"United States"},{"startIP":"2759262208","endIP":"2759327743","countryCode":"US","countryName":"United States"},{"startIP":"2759327744","endIP":"2759393279","countryCode":"US","countryName":"United States"},{"startIP":"2759393280","endIP":"2759458815","countryCode":"US","countryName":"United States"},{"startIP":"2759458816","endIP":"2759524351","countryCode":"US","countryName":"United States"},{"startIP":"2759524352","endIP":"2759589887","countryCode":"US","countryName":"United States"},{"startIP":"2759589888","endIP":"2759655423","countryCode":"KR","countryName":"South Korea"},{"startIP":"2759655424","endIP":"2759720959","countryCode":"KR","countryName":"South Korea"},{"startIP":"2759720960","endIP":"2759852031","countryCode":"PL","countryName":"Poland"},{"startIP":"2759852032","endIP":"2759917567","countryCode":"CH","countryName":"Switzerland"},{"startIP":"2759917568","endIP":"2759983103","countryCode":"FR","countryName":"France"},{"startIP":"2759983104","endIP":"2760048639","countryCode":"IT","countryName":"Italy"},{"startIP":"2760048640","endIP":"2760114175","countryCode":"FR","countryName":"France"},{"startIP":"2760114176","endIP":"2760179711","countryCode":"IT","countryName":"Italy"},{"startIP":"2760179712","endIP":"2760245247","countryCode":"DE","countryName":"Germany"},{"startIP":"2760245248","endIP":"2760310783","countryCode":"GB","countryName":"Great Britain (UK)"},{"startIP":"2760310784","endIP":"2760376319","countryCode":"SE","countryName":"Sweden"},{"startIP":"2760376320","endIP":"2760441855","countryCode":"GB","countryName":"Great Britain (UK)"},{"startIP":"2760441856","endIP":"2760507391","countryCode":"GB","countryName":"Great Britain (UK)"},{"startIP":"2760507392","endIP":"2760511487","countryCode":"RU","countryName":"Russian Federation"},{"startIP":"2760511488","endIP":"2760513535","countryCode":"IR","countryName":"Iran"},{"startIP":"2760513536","endIP":"2760515583","countryCode":"NL","countryName":"Netherlands"},{"startIP":"2760515584","endIP":"2760517631","countryCode":"RU","countryName":"Russian Federation"},{"startIP":"2760517632","endIP":"2760519679","countryCode":"KZ","countryName":"Kazakhstan"},{"startIP":"2760519680","endIP":"2760521727","countryCode":"IT","countryName":"Italy"},{"startIP":"2760521728","endIP":"2760523775","countryCode":"FR","countryName":"France"},{"startIP":"2760523776","endIP":"2760527871","countryCode":"CH","countryName":"Switzerland"},{"startIP":"2760527872","endIP":"2760529919","countryCode":"GB","countryName":"Great Britain (UK)"},{"startIP":"2760529920","endIP":"2760531967","countryCode":"RU","countryName":"Russian Federation"},{"startIP":"2760531968","endIP":"2760534015","countryCode":"IR","countryName":"Iran"},{"startIP":"2760534016","endIP":"2760536063","countryCode":"BE","countryName":"Belgium"},{"startIP":"2760536064","endIP":"2760540159","countryCode":"IL","countryName":"Israel"},{"startIP":"2760540160","endIP":"2760556543","countryCode":"RO","countryName":"Romania"},{"startIP":"2760556544","endIP":"2760558591","countryCode":"DE","countryName":"Germany"},{"startIP":"2760558592","endIP":"2760560639","countryCode":"ES","countryName":"Spain"},{"startIP":"2760560640","endIP":"2760562687","countryCode":"ES","countryName":"Spain"},{"startIP":"2760562688","endIP":"2760564735","countryCode":"BG","countryName":"Bulgaria"},{"startIP":"2760564736","endIP":"2760566783","countryCode":"GB","countryName":"Great Britain (UK)"},{"startIP":"2760566784","endIP":"2760568831","countryCode":"IQ","countryName":"Iraq"},{"startIP":"2760568832","endIP":"2760570879","countryCode":"FR","countryName":"France"},{"startIP":"2760570880","endIP":"2760572927","countryCode":"NL","countryName":"Netherlands"},{"startIP":"2760572928","endIP":"2760638463","countryCode":"DE","countryName":"Germany"},{"startIP":"2760638464","endIP":"2760703999","countryCode":"NL","countryName":"Netherlands"},{"startIP":"2760704000","endIP":"2760769535","countryCode":"FI","countryName":"Finland"},{"startIP":"2760769536","endIP":"2760835071","countryCode":"IT","countryName":"Italy"},{"startIP":"2760835072","endIP":"2760900607","countryCode":"GB","countryName":"Great Britain (UK)"},{"startIP":"2760900608","endIP":"2760966143","countryCode":"US","countryName":"United States"},{"startIP":"2760966144","endIP":"2761031679","countryCode":"US","countryName":"United States"},{"startIP":"2761031680","endIP":"2761424895","countryCode":"ZA","countryName":"South Africa"},{"startIP":"2761424896","endIP":"2761490431","countryCode":"US","countryName":"United States"},{"startIP":"2761490432","endIP":"2761555967","countryCode":"US","countryName":"United States"},{"startIP":"2761555968","endIP":"2761621503","countryCode":"US","countryName":"United States"},{"startIP":"2761621504","endIP":"2761687039","countryCode":"ZA","countryName":"South Africa"},{"startIP":"2761687040","endIP":"2761752575","countryCode":"US","countryName":"United States"},{"startIP":"2761752576","endIP":"2761818111","countryCode":"US","countryName":"United States"},{"startIP":"2761818112","endIP":"2761883647","countryCode":"US","countryName":"United States"},{"startIP":"2761883648","endIP":"2761949183","countryCode":"US","countryName":"United States"},{"startIP":"2762014720","endIP":"2762080255","countryCode":"JP","countryName":"Japan"},{"startIP":"2762080256","endIP":"2762145791","countryCode":"JP","countryName":"Japan"},{"startIP":"2762211328","endIP":"2762276863","countryCode":"IN","countryName":"India"},{"startIP":"2762276864","endIP":"2762342399","countryCode":"US","countryName":"United States"},{"startIP":"2762342400","endIP":"2762407935","countryCode":"CA","countryName":"Canada"},{"startIP":"2762407936","endIP":"2762473471","countryCode":"US","countryName":"United States"},{"startIP":"2762473472","endIP":"2762539007","countryCode":"US","countryName":"United States"},{"startIP":"2762539008","endIP":"2763063295","countryCode":"US","countryName":"United States"},{"startIP":"2763063296","endIP":"2763096063","countryCode":"FR","countryName":"France"},{"startIP":"2763096064","endIP":"2763104255","countryCode":"GB","countryName":"Great Britain (UK)"},{"startIP":"2763104256","endIP":"2763106303","countryCode":"DE","countryName":"Germany"},{"startIP":"2763106304","endIP":"2763108351","countryCode":"DE","countryName":"Germany"},{"startIP":"2763108352","endIP":"2763110399","countryCode":"RU","countryName":"Russian Federation"},{"startIP":"2763110400","endIP":"2763112447","countryCode":"GB","countryName":"Great Britain (UK)"},{"startIP":"2763112448","endIP":"2763128831","countryCode":"BY","countryName":"Belarus"},{"startIP":"2763128832","endIP":"2763194367","countryCode":"CA","countryName":"Canada"},{"startIP":"2763194368","endIP":"2763259903","countryCode":"US","countryName":"United States"},{"startIP":"2763259904","endIP":"2763915263","countryCode":"US","countryName":"United States"},{"startIP":"2763915264","endIP":"2764242943","countryCode":"US","countryName":"United States"},{"startIP":"2764242944","endIP":"2764308479","countryCode":"US","countryName":"United States"},{"startIP":"2764308480","endIP":"2764439551","countryCode":"US","countryName":"United States"},{"startIP":"2764439552","endIP":"2764505087","countryCode":"US","countryName":"United States"},{"startIP":"2764505088","endIP":"2764570623","countryCode":"US","countryName":"United States"},{"startIP":"2764570624","endIP":"2764636159","countryCode":"US","countryName":"United States"},{"startIP":"2764636160","endIP":"2764701695","countryCode":"US","countryName":"United States"},{"startIP":"2764701696","endIP":"2765029375","countryCode":"US","countryName":"United States"},{"startIP":"2765029376","endIP":"2765422591","countryCode":"US","countryName":"United States"},{"startIP":"2765422592","endIP":"2765488127","countryCode":"US","countryName":"United States"},{"startIP":"2765488128","endIP":"2765553663","countryCode":"US","countryName":"United States"},{"startIP":"2765553664","endIP":"2765561855","countryCode":"CY","countryName":"Cyprus"},{"startIP":"2765561856","endIP":"2765563903","countryCode":"FI","countryName":"Finland"},{"startIP":"2765563904","endIP":"2765565951","countryCode":"IR","countryName":"Iran"},{"startIP":"2765565952","endIP":"2765567999","countryCode":"RU","countryName":"Russian Federation"},{"startIP":"2765568000","endIP":"2765570047","countryCode":"IR","countryName":"Iran"},{"startIP":"2765570048","endIP":"2765574143","countryCode":"RU","countryName":"Russian Federation"},{"startIP":"2765574144","endIP":"2765578239","countryCode":"RU","countryName":"Russian Federation"},{"startIP":"2765578240","endIP":"2765580287","countryCode":"AZ","countryName":"Azerbaijan"},{"startIP":"2765580288","endIP":"2765582335","countryCode":"GB","countryName":"Great Britain (UK)"},{"startIP":"2765582336","endIP":"2765586431","countryCode":"CZ","countryName":"Czech Republic"},{"startIP":"2765586432","endIP":"2765619199","countryCode":"IR","countryName":"Iran"},{"startIP":"2765619200","endIP":"2765684735","countryCode":"US","countryName":"United States"},{"startIP":"2765684736","endIP":"2765750271","countryCode":"US","countryName":"United States"},{"startIP":"2765750272","endIP":"2765815807","countryCode":"US","countryName":"United States"},{"startIP":"2765815808","endIP":"2765881343","countryCode":"US","countryName":"United States"},{"startIP":"2765881344","endIP":"2765946879","countryCode":"US","countryName":"United States"},{"startIP":"2765946880","endIP":"2766012415","countryCode":"US","countryName":"United States"},{"startIP":"2766012416","endIP":"2766077951","countryCode":"US","countryName":"United States"},{"startIP":"2766077952","endIP":"2766143487","countryCode":"US","countryName":"United States"},{"startIP":"2766143488","endIP":"2766209023","countryCode":"US","countryName":"United States"},{"startIP":"2766209024","endIP":"2766274559","countryCode":"US","countryName":"United States"},{"startIP":"2766274560","endIP":"2766340095","countryCode":"US","countryName":"United States"},{"startIP":"2766340096","endIP":"2768240639","countryCode":"US","countryName":"United States"},{"startIP":"2768306176","endIP":"2768371711","countryCode":"US","countryName":"United States"},{"startIP":"2768371712","endIP":"2768437247","countryCode":"US","countryName":"United States"},{"startIP":"2768437248","endIP":"2768633855","countryCode":"ZA","countryName":"South Africa"},{"startIP":"2768633856","endIP":"2768699391","countryCode":"US","countryName":"United States"},{"startIP":"2768699392","endIP":"2768764927","countryCode":"US","countryName":"United States"},{"startIP":"2768764928","endIP":"2769027071","countryCode":"ZA","countryName":"South Africa"},{"startIP":"2769027072","endIP":"2769092607","countryCode":"AU","countryName":"Australia"},{"startIP":"2769092608","endIP":"2769158143","countryCode":"US","countryName":"United States"},{"startIP":"2769158144","endIP":"2769223679","countryCode":"JP","countryName":"Japan"},{"startIP":"2769485824","endIP":"2769551359","countryCode":"US","countryName":"United States"},{"startIP":"2769551360","endIP":"2769616895","countryCode":"US","countryName":"United States"},{"startIP":"2769616896","endIP":"2769682431","countryCode":"SG","countryName":"Singapore"},{"startIP":"2769682432","endIP":"2769747967","countryCode":"US","countryName":"United States"},{"startIP":"2769747968","endIP":"2769813503","countryCode":"CA","countryName":"Canada"},{"startIP":"2769813504","endIP":"2769879039","countryCode":"US","countryName":"United States"},{"startIP":"2769879040","endIP":"2769944575","countryCode":"ZA","countryName":"South Africa"},{"startIP":"2769944576","endIP":"2770010111","countryCode":"US","countryName":"United States"},{"startIP":"2770010112","endIP":"2770075647","countryCode":"US","countryName":"United States"},{"startIP":"2770075648","endIP":"2770141183","countryCode":"US","countryName":"United States"},{"startIP":"2770141184","endIP":"2770206719","countryCode":"US","countryName":"United States"},{"startIP":"2770206720","endIP":"2770272255","countryCode":"US","countryName":"United States"},{"startIP":"2770272256","endIP":"2770337791","countryCode":"AU","countryName":"Australia"},{"startIP":"2770337792","endIP":"2771451903","countryCode":"US","countryName":"United States"},{"startIP":"2772434944","endIP":"2772500479","countryCode":"US","countryName":"United States"},{"startIP":"2772500480","endIP":"2772566015","countryCode":"US","countryName":"United States"},{"startIP":"2772566016","endIP":"2772631551","countryCode":"US","countryName":"United States"},{"startIP":"2772697088","endIP":"2772762623","countryCode":"US","countryName":"United States"},{"startIP":"2772762624","endIP":"2772828159","countryCode":"AU","countryName":"Australia"},{"startIP":"2772828160","endIP":"2772893695","countryCode":"US","countryName":"United States"},{"startIP":"2772893696","endIP":"2772959231","countryCode":"US","countryName":"United States"},{"startIP":"2772959232","endIP":"2773024767","countryCode":"CZ","countryName":"Czech Republic"},{"startIP":"2773090304","endIP":"2773155839","countryCode":"US","countryName":"United States"},{"startIP":"2773155840","endIP":"2773221375","countryCode":"US","countryName":"United States"},{"startIP":"2773221376","endIP":"2773286911","countryCode":"JP","countryName":"Japan"},{"startIP":"2773286912","endIP":"2773352447","countryCode":"US","countryName":"United States"},{"startIP":"2773352448","endIP":"2773417983","countryCode":"CA","countryName":"Canada"},{"startIP":"2773417984","endIP":"2773483519","countryCode":"US","countryName":"United States"},{"startIP":"2773483520","endIP":"2773549055","countryCode":"US","countryName":"United States"},{"startIP":"2773549056","endIP":"2773614591","countryCode":"US","countryName":"United States"},{"startIP":"2773614592","endIP":"2773680127","countryCode":"US","countryName":"United States"},{"startIP":"2773680128","endIP":"2773745663","countryCode":"US","countryName":"United States"},{"startIP":"2773745664","endIP":"2773811199","countryCode":"NZ","countryName":"New Zealand"},{"startIP":"2773811200","endIP":"2773876735","countryCode":"US","countryName":"United States"},{"startIP":"2773876736","endIP":"2773942271","countryCode":"AU","countryName":"Australia"},{"startIP":"2773942272","endIP":"2774007807","countryCode":"US","countryName":"United States"},{"startIP":"2774007808","endIP":"2774073343","countryCode":"US","countryName":"United States"},{"startIP":"2774073344","endIP":"2774138879","countryCode":"US","countryName":"United States"},{"startIP":"2774204416","endIP":"2774269951","countryCode":"US","countryName":"United States"},{"startIP":"2774269952","endIP":"2774335487","countryCode":"US","countryName":"United States"},{"startIP":"2774335488","endIP":"2774401023","countryCode":"JP","countryName":"Japan"},{"startIP":"2774401024","endIP":"2774466559","countryCode":"US","countryName":"United States"},{"startIP":"2774466560","endIP":"2774532095","countryCode":"US","countryName":"United States"},{"startIP":"2774532096","endIP":"2774597631","countryCode":"JP","countryName":"Japan"},{"startIP":"2774597632","endIP":"2774663167","countryCode":"US","countryName":"United States"},{"startIP":"2774663168","endIP":"2774728703","countryCode":"NI","countryName":"Nicaragua"},{"startIP":"2774728704","endIP":"2774794239","countryCode":"JP","countryName":"Japan"},{"startIP":"2774794240","endIP":"2774827007","countryCode":"JP","countryName":"Japan"},{"startIP":"2774827008","endIP":"2774843391","countryCode":"JP","countryName":"Japan"},{"startIP":"2774843392","endIP":"2774859775","countryCode":"JP","countryName":"Japan"},{"startIP":"2774859776","endIP":"2774925311","countryCode":"JP","countryName":"Japan"},{"startIP":"2774925312","endIP":"2774990847","countryCode":"JP","countryName":"Japan"},{"startIP":"2774990848","endIP":"2775056383","countryCode":"US","countryName":"United States"},{"startIP":"2775056384","endIP":"2775121919","countryCode":"US","countryName":"United States"},{"startIP":"2775121920","endIP":"2775187455","countryCode":"US","countryName":"United States"},{"startIP":"2775187456","endIP":"2775252991","countryCode":"US","countryName":"United States"},{"startIP":"2775252992","endIP":"2775318527","countryCode":"US","countryName":"United States"},{"startIP":"2775318528","endIP":"2775384063","countryCode":"JP","countryName":"Japan"},{"startIP":"2775384064","endIP":"2775449599","countryCode":"US","countryName":"United States"},{"startIP":"2775449600","endIP":"2775515135","countryCode":"US","countryName":"United States"},{"startIP":"2775515136","endIP":"2775580671","countryCode":"US","countryName":"United States"},{"startIP":"2775580672","endIP":"2775646207","countryCode":"US","countryName":"United States"},{"startIP":"2775646208","endIP":"2775711743","countryCode":"US","countryName":"United States"},{"startIP":"2775711744","endIP":"2775777279","countryCode":"NL","countryName":"Netherlands"},{"startIP":"2775777280","endIP":"2775842815","countryCode":"CA","countryName":"Canada"},{"startIP":"2775842816","endIP":"2775908351","countryCode":"US","countryName":"United States"},{"startIP":"2775908352","endIP":"2775973887","countryCode":"US","countryName":"United States"},{"startIP":"2775973888","endIP":"2776039423","countryCode":"AU","countryName":"Australia"},{"startIP":"2776039424","endIP":"2776104959","countryCode":"US","countryName":"United States"},{"startIP":"2776104960","endIP":"2776170495","countryCode":"US","countryName":"United States"},{"startIP":"2776170496","endIP":"2776236031","countryCode":"US","countryName":"United States"},{"startIP":"2776236032","endIP":"2776301567","countryCode":"US","countryName":"United States"},{"startIP":"2776301568","endIP":"2776367103","countryCode":"US","countryName":"United States"},{"startIP":"2776367104","endIP":"2776432639","countryCode":"US","countryName":"United States"},{"startIP":"2776432640","endIP":"2776498175","countryCode":"US","countryName":"United States"},{"startIP":"2776498176","endIP":"2776563711","countryCode":"US","countryName":"United States"},{"startIP":"2776563712","endIP":"2776629247","countryCode":"US","countryName":"United States"},{"startIP":"2776629248","endIP":"2776694783","countryCode":"US","countryName":"United States"},{"startIP":"2776694784","endIP":"2776760319","countryCode":"US","countryName":"United States"},{"startIP":"2776760320","endIP":"2776825855","countryCode":"US","countryName":"United States"},{"startIP":"2776825856","endIP":"2776891391","countryCode":"US","countryName":"United States"},{"startIP":"2776891392","endIP":"2776956927","countryCode":"KR","countryName":"South Korea"},{"startIP":"2776956928","endIP":"2777022463","countryCode":"KR","countryName":"South Korea"},{"startIP":"2777022464","endIP":"2777087999","countryCode":"US","countryName":"United States"},{"startIP":"2777088000","endIP":"2777153535","countryCode":"US","countryName":"United States"},{"startIP":"2777153536","endIP":"2777219071","countryCode":"US","countryName":"United States"},{"startIP":"2777219072","endIP":"2777284607","countryCode":"US","countryName":"United States"},{"startIP":"2777284608","endIP":"2777350143","countryCode":"US","countryName":"United States"},{"startIP":"2777350144","endIP":"2777415679","countryCode":"US","countryName":"United States"},{"startIP":"2777415680","endIP":"2777481215","countryCode":"US","countryName":"United States"},{"startIP":"2777481216","endIP":"2777546751","countryCode":"KR","countryName":"South Korea"},{"startIP":"2777546752","endIP":"2777612287","countryCode":"AU","countryName":"Australia"},{"startIP":"2777612288","endIP":"2777677823","countryCode":"ZA","countryName":"South Africa"},{"startIP":"2777677824","endIP":"2777939967","countryCode":"ZA","countryName":"South Africa"},{"startIP":"2777939968","endIP":"2778071039","countryCode":"ZA","countryName":"South Africa"},{"startIP":"2778071040","endIP":"2778136575","countryCode":"US","countryName":"United States"},{"startIP":"2778136576","endIP":"2778202111","countryCode":"US","countryName":"United States"},{"startIP":"2778202112","endIP":"2778267647","countryCode":"US","countryName":"United States"},{"startIP":"2778267648","endIP":"2778333183","countryCode":"US","countryName":"United States"},{"startIP":"2778333184","endIP":"2778398719","countryCode":"CA","countryName":"Canada"},{"startIP":"2778398720","endIP":"2778464255","countryCode":"US","countryName":"United States"},{"startIP":"2778464256","endIP":"2778529791","countryCode":"US","countryName":"United States"},{"startIP":"2778529792","endIP":"2778595327","countryCode":"US","countryName":"United States"},{"startIP":"2778595328","endIP":"2778660863","countryCode":"US","countryName":"United States"},{"startIP":"2778660864","endIP":"2778726399","countryCode":"US","countryName":"United States"},{"startIP":"2778726400","endIP":"2778791935","countryCode":"US","countryName":"United States"},{"startIP":"2778791936","endIP":"2778857471","countryCode":"US","countryName":"United States"},{"startIP":"2778857472","endIP":"2778923007","countryCode":"US","countryName":"United States"},{"startIP":"2778923008","endIP":"2778988543","countryCode":"US","countryName":"United States"},{"startIP":"2778988544","endIP":"2779054079","countryCode":"US","countryName":"United States"},{"startIP":"2779054080","endIP":"2779119615","countryCode":"ZA","countryName":"South Africa"},{"startIP":"2779119616","endIP":"2779185151","countryCode":"US","countryName":"United States"},{"startIP":"2779185152","endIP":"2779250687","countryCode":"US","countryName":"United States"},{"startIP":"2779250688","endIP":"2779316223","countryCode":"US","countryName":"United States"},{"startIP":"2779381760","endIP":"2779447295","countryCode":"US","countryName":"United States"},{"startIP":"2779447296","endIP":"2779512831","countryCode":"US","countryName":"United States"},{"startIP":"2779512832","endIP":"2779578367","countryCode":"US","countryName":"United States"},{"startIP":"2779578368","endIP":"2779643903","countryCode":"US","countryName":"United States"},{"startIP":"2779643904","endIP":"2779709439","countryCode":"US","countryName":"United States"},{"startIP":"2779709440","endIP":"2779774975","countryCode":"US","countryName":"United States"},{"startIP":"2779774976","endIP":"2779840511","countryCode":"US","countryName":"United States"},{"startIP":"2779840512","endIP":"2779906047","countryCode":"US","countryName":"United States"},{"startIP":"2779906048","endIP":"2779971583","countryCode":"CA","countryName":"Canada"},{"startIP":"2779971584","endIP":"2780037119","countryCode":"US","countryName":"United States"},{"startIP":"2780037120","endIP":"2780102655","countryCode":"ZA","countryName":"South Africa"},{"startIP":"2780102656","endIP":"2780168191","countryCode":"US","countryName":"United States"},{"startIP":"2780168192","endIP":"2780233727","countryCode":"CL","countryName":"Chile"},{"startIP":"2780233728","endIP":"2780299263","countryCode":"CL","countryName":"Chile"},{"startIP":"2780299264","endIP":"2780364799","countryCode":"US","countryName":"United States"},{"startIP":"2780364800","endIP":"2780430335","countryCode":"CA","countryName":"Canada"},{"startIP":"2780430336","endIP":"2780495871","countryCode":"KR","countryName":"South Korea"},{"startIP":"2780495872","endIP":"2780561407","countryCode":"AU","countryName":"Australia"},{"startIP":"2780561408","endIP":"2780626943","countryCode":"US","countryName":"United States"},{"startIP":"2780626944","endIP":"2780692479","countryCode":"US","countryName":"United States"},{"startIP":"2780692480","endIP":"2780758015","countryCode":"US","countryName":"United States"},{"startIP":"2780758016","endIP":"2780823551","countryCode":"AU","countryName":"Australia"},{"startIP":"2780823552","endIP":"2780889087","countryCode":"US","countryName":"United States"},{"startIP":"2780889088","endIP":"2780954623","countryCode":"US","countryName":"United States"},{"startIP":"2780954624","endIP":"2781020159","countryCode":"KR","countryName":"South Korea"},{"startIP":"2781020160","endIP":"2781085695","countryCode":"US","countryName":"United States"},{"startIP":"2781085696","endIP":"2781151231","countryCode":"US","countryName":"United States"},{"startIP":"2781151232","endIP":"2781282303","countryCode":"US","countryName":"United States"},{"startIP":"2781282304","endIP":"2781347839","countryCode":"US","countryName":"United States"},{"startIP":"2781347840","endIP":"2781413375","countryCode":"US","countryName":"United States"},{"startIP":"2781413376","endIP":"2781478911","countryCode":"US","countryName":"United States"},{"startIP":"2781478912","endIP":"2781544447","countryCode":"HK","countryName":"Hong Kong"},{"startIP":"2781544448","endIP":"2781609983","countryCode":"US","countryName":"United States"},{"startIP":"2781609984","endIP":"2781675519","countryCode":"US","countryName":"United States"},{"startIP":"2781675520","endIP":"2781741055","countryCode":"NZ","countryName":"New Zealand"},{"startIP":"2781741056","endIP":"2781806591","countryCode":"US","countryName":"United States"},{"startIP":"2781806592","endIP":"2781872127","countryCode":"US","countryName":"United States"},{"startIP":"2781872128","endIP":"2781937663","countryCode":"US","countryName":"United States"},{"startIP":"2781937664","endIP":"2782003199","countryCode":"TH","countryName":"Thailand"},{"startIP":"2782134272","endIP":"2782167039","countryCode":"US","countryName":"United States"},{"startIP":"2782167040","endIP":"2782199807","countryCode":"US","countryName":"United States"},{"startIP":"2782199808","endIP":"2782265343","countryCode":"KR","countryName":"South Korea"},{"startIP":"2782265344","endIP":"2782330879","countryCode":"US","countryName":"United States"},{"startIP":"2782330880","endIP":"2782396415","countryCode":"US","countryName":"United States"},{"startIP":"2782396416","endIP":"2782461951","countryCode":"US","countryName":"United States"},{"startIP":"2782461952","endIP":"2782527487","countryCode":"US","countryName":"United States"},{"startIP":"2782527488","endIP":"2782593023","countryCode":"US","countryName":"United States"},{"startIP":"2782593024","endIP":"2782658559","countryCode":"US","countryName":"United States"},{"startIP":"2782658560","endIP":"2782724095","countryCode":"PH","countryName":"Philippines"},{"startIP":"2782724096","endIP":"2782789631","countryCode":"US","countryName":"United States"},{"startIP":"2782789632","endIP":"2782855167","countryCode":"CH","countryName":"Switzerland"},{"startIP":"2782855168","endIP":"2782920703","countryCode":"US","countryName":"United States"},{"startIP":"2782920704","endIP":"2782986239","countryCode":"US","countryName":"United States"},{"startIP":"2782986240","endIP":"2783019007","countryCode":"US","countryName":"United States"},{"startIP":"2783019008","endIP":"2783035391","countryCode":"US","countryName":"United States"},{"startIP":"2783035392","endIP":"2783051775","countryCode":"US","countryName":"United States"},{"startIP":"2783051776","endIP":"2783117311","countryCode":"US","countryName":"United States"},{"startIP":"2783117312","endIP":"2783182847","countryCode":"US","countryName":"United States"},{"startIP":"2783182848","endIP":"2783248383","countryCode":"AU","countryName":"Australia"},{"startIP":"2783248384","endIP":"2783313919","countryCode":"KR","countryName":"South Korea"},{"startIP":"2783313920","endIP":"2783379455","countryCode":"US","countryName":"United States"},{"startIP":"2783379456","endIP":"2783444991","countryCode":"ZA","countryName":"South Africa"},{"startIP":"2783444992","endIP":"2783510527","countryCode":"US","countryName":"United States"},{"startIP":"2783510528","endIP":"2783576063","countryCode":"ZA","countryName":"South Africa"},{"startIP":"2783576064","endIP":"2783641599","countryCode":"US","countryName":"United States"},{"startIP":"2783641600","endIP":"2783707135","countryCode":"US","countryName":"United States"},{"startIP":"2783707136","endIP":"2783772671","countryCode":"US","countryName":"United States"},{"startIP":"2783772672","endIP":"2783838207","countryCode":"US","countryName":"United States"},{"startIP":"2783838208","endIP":"2783903743","countryCode":"US","countryName":"United States"},{"startIP":"2783903744","endIP":"2783969279","countryCode":"US","countryName":"United States"},{"startIP":"2783969280","endIP":"2784034815","countryCode":"AU","countryName":"Australia"},{"startIP":"2784034816","endIP":"2784100351","countryCode":"JP","countryName":"Japan"},{"startIP":"2784100352","endIP":"2784165887","countryCode":"JP","countryName":"Japan"},{"startIP":"2784165888","endIP":"2784231423","countryCode":"KR","countryName":"South Korea"},{"startIP":"2784231424","endIP":"2784296959","countryCode":"KR","countryName":"South Korea"},{"startIP":"2784296960","endIP":"2784362495","countryCode":"US","countryName":"United States"},{"startIP":"2784362496","endIP":"2784428031","countryCode":"KR","countryName":"South Korea"},{"startIP":"2784428032","endIP":"2784493567","countryCode":"US","countryName":"United States"},{"startIP":"2784493568","endIP":"2784559103","countryCode":"US","countryName":"United States"},{"startIP":"2784559104","endIP":"2784624639","countryCode":"US","countryName":"United States"},{"startIP":"2784624640","endIP":"2784690175","countryCode":"US","countryName":"United States"},{"startIP":"2784690176","endIP":"2784755711","countryCode":"US","countryName":"United States"},{"startIP":"2784755712","endIP":"2784821247","countryCode":"US","countryName":"United States"},{"startIP":"2784821248","endIP":"2784886783","countryCode":"US","countryName":"United States"},{"startIP":"2784886784","endIP":"2784952319","countryCode":"US","countryName":"United States"},{"startIP":"2785017856","endIP":"2785148927","countryCode":"US","countryName":"United States"},{"startIP":"2785148928","endIP":"2785542143","countryCode":"US","countryName":"United States"},{"startIP":"2785542144","endIP":"2786066431","countryCode":"CH","countryName":"Switzerland"},{"startIP":"2786066432","endIP":"2786131967","countryCode":"US","countryName":"United States"},{"startIP":"2786131968","endIP":"2786263039","countryCode":"US","countryName":"United States"},{"startIP":"2786263040","endIP":"2786328575","countryCode":"US","countryName":"United States"},{"startIP":"2786328576","endIP":"2786394111","countryCode":"US","countryName":"United States"},{"startIP":"2786394112","endIP":"2787115007","countryCode":"US","countryName":"United States"},{"startIP":"2787115008","endIP":"2787704831","countryCode":"US","countryName":"United States"},{"startIP":"2787704832","endIP":"2787770367","countryCode":"US","countryName":"United States"},{"startIP":"2787770368","endIP":"2787966975","countryCode":"US","countryName":"United States"},{"startIP":"2787966976","endIP":"2788032511","countryCode":"US","countryName":"United States"},{"startIP":"2788032512","endIP":"2788163583","countryCode":"US","countryName":"United States"},{"startIP":"2788229120","endIP":"2788261887","countryCode":"US","countryName":"United States"},{"startIP":"2788261888","endIP":"2788294655","countryCode":"GB","countryName":"Great Britain (UK)"},{"startIP":"2788294656","endIP":"2788556799","countryCode":"US","countryName":"United States"},{"startIP":"2788556800","endIP":"2788622335","countryCode":"US","countryName":"United States"},{"startIP":"2788622336","endIP":"2788687871","countryCode":"US","countryName":"United States"},{"startIP":"2788687872","endIP":"2788753407","countryCode":"US","countryName":"United States"},{"startIP":"2788753408","endIP":"2788818943","countryCode":"US","countryName":"United States"},{"startIP":"2788818944","endIP":"2788884479","countryCode":"US","countryName":"United States"},{"startIP":"2788884480","endIP":"2788950015","countryCode":"US","countryName":"United States"},{"startIP":"2788950016","endIP":"2789015551","countryCode":"US","countryName":"United States"},{"startIP":"2789015552","endIP":"2789081087","countryCode":"US","countryName":"United States"},{"startIP":"2789146624","endIP":"2789179391","countryCode":"US","countryName":"United States"},{"startIP":"2789179392","endIP":"2789187583","countryCode":"US","countryName":"United States"},{"startIP":"2789187584","endIP":"2789195775","countryCode":"US","countryName":"United States"},{"startIP":"2789195776","endIP":"2789203967","countryCode":"US","countryName":"United States"},{"startIP":"2789203968","endIP":"2789212159","countryCode":"US","countryName":"United States"},{"startIP":"2789212160","endIP":"2789277695","countryCode":"AU","countryName":"Australia"},{"startIP":"2789277696","endIP":"2789343231","countryCode":"NZ","countryName":"New Zealand"},{"startIP":"2789343232","endIP":"2789408767","countryCode":"US","countryName":"United States"},{"startIP":"2789408768","endIP":"2789474303","countryCode":"US","countryName":"United States"},{"startIP":"2789474304","endIP":"2789539839","countryCode":"US","countryName":"United States"},{"startIP":"2789539840","endIP":"2789605375","countryCode":"US","countryName":"United States"},{"startIP":"2789605376","endIP":"2789670911","countryCode":"US","countryName":"United States"},{"startIP":"2789670912","endIP":"2789736447","countryCode":"US","countryName":"United States"},{"startIP":"2789736448","endIP":"2789801983","countryCode":"US","countryName":"United States"},{"startIP":"2789801984","endIP":"2789867519","countryCode":"US","countryName":"United States"},{"startIP":"2789867520","endIP":"2789933055","countryCode":"US","countryName":"United States"},{"startIP":"2789933056","endIP":"2789998591","countryCode":"CL","countryName":"Chile"},{"startIP":"2789998592","endIP":"2790064127","countryCode":"US","countryName":"United States"},{"startIP":"2790064128","endIP":"2790129663","countryCode":"US","countryName":"United States"},{"startIP":"2790195200","endIP":"2790260735","countryCode":"KR","countryName":"South Korea"},{"startIP":"2790260736","endIP":"2790326271","countryCode":"US","countryName":"United States"},{"startIP":"2790391808","endIP":"2790457343","countryCode":"US","countryName":"United States"},{"startIP":"2790457344","endIP":"2790522879","countryCode":"NZ","countryName":"New Zealand"},{"startIP":"2790522880","endIP":"2790588415","countryCode":"US","countryName":"United States"},{"startIP":"2790588416","endIP":"2790653951","countryCode":"ZA","countryName":"South Africa"},{"startIP":"2790653952","endIP":"2790719487","countryCode":"US","countryName":"United States"},{"startIP":"2790719488","endIP":"2790785023","countryCode":"SA","countryName":"Saudi Arabia"},{"startIP":"2790850560","endIP":"2790916095","countryCode":"US","countryName":"United States"},{"startIP":"2790916096","endIP":"2790981631","countryCode":"US","countryName":"United States"},{"startIP":"2790981632","endIP":"2791047167","countryCode":"US","countryName":"United States"},{"startIP":"2791047168","endIP":"2791112703","countryCode":"US","countryName":"United States"},{"startIP":"2791112704","endIP":"2791178239","countryCode":"US","countryName":"United States"},{"startIP":"2791178240","endIP":"2791243775","countryCode":"US","countryName":"United States"},{"startIP":"2791243776","endIP":"2791309311","countryCode":"US","countryName":"United States"},{"startIP":"2791309312","endIP":"2791374847","countryCode":"US","countryName":"United States"},{"startIP":"2791374848","endIP":"2791440383","countryCode":"US","countryName":"United States"},{"startIP":"2791440384","endIP":"2791505919","countryCode":"US","countryName":"United States"},{"startIP":"2791505920","endIP":"2791571455","countryCode":"US","countryName":"United States"},{"startIP":"2791571456","endIP":"2791636991","countryCode":"JP","countryName":"Japan"},{"startIP":"2791636992","endIP":"2791702527","countryCode":"US","countryName":"United States"},{"startIP":"2791702528","endIP":"2791768063","countryCode":"US","countryName":"United States"},{"startIP":"2791768064","endIP":"2791833599","countryCode":"KR","countryName":"South Korea"},{"startIP":"2791833600","endIP":"2791899135","countryCode":"KR","countryName":"South Korea"},{"startIP":"2791899136","endIP":"2791964671","countryCode":"US","countryName":"United States"},{"startIP":"2792030208","endIP":"2792095743","countryCode":"US","countryName":"United States"},{"startIP":"2792095744","endIP":"2792161279","countryCode":"US","countryName":"United States"},{"startIP":"2792161280","endIP":"2792226815","countryCode":"US","countryName":"United States"},{"startIP":"2792226816","endIP":"2792292351","countryCode":"CL","countryName":"Chile"},{"startIP":"2792292352","endIP":"2792357887","countryCode":"CN","countryName":"China"},{"startIP":"2792357888","endIP":"2792423423","countryCode":"US","countryName":"United States"},{"startIP":"2792423424","endIP":"2792488959","countryCode":"US","countryName":"United States"},{"startIP":"2792488960","endIP":"2792554495","countryCode":"BO","countryName":"Bolivia"},{"startIP":"2792554496","endIP":"2792620031","countryCode":"US","countryName":"United States"},{"startIP":"2792620032","endIP":"2792685567","countryCode":"US","countryName":"United States"},{"startIP":"2792685568","endIP":"2792751103","countryCode":"US","countryName":"United States"},{"startIP":"2792751104","endIP":"2792816639","countryCode":"JP","countryName":"Japan"},{"startIP":"2792816640","endIP":"2792882175","countryCode":"JP","countryName":"Japan"},{"startIP":"2792882176","endIP":"2792947711","countryCode":"AU","countryName":"Australia"},{"startIP":"2792947712","endIP":"2793013247","countryCode":"SG","countryName":"Singapore"},{"startIP":"2793013248","endIP":"2793078783","countryCode":"US","countryName":"United States"},{"startIP":"2793078784","endIP":"2793144319","countryCode":"US","countryName":"United States"},{"startIP":"2793144320","endIP":"2793209855","countryCode":"US","countryName":"United States"},{"startIP":"2793209856","endIP":"2793275391","countryCode":"KR","countryName":"South Korea"},{"startIP":"2793275392","endIP":"2793340927","countryCode":"US","countryName":"United States"},{"startIP":"2793340928","endIP":"2793406463","countryCode":"US","countryName":"United States"}]