[{"startIP":"402653184","endIP":"403701759","countryCode":"US","countryName":"United States"},{"startIP":"403701760","endIP":"404226047","countryCode":"US","countryName":"United States"},{"startIP":"404226048","endIP":"404619263","countryCode":"US","countryName":"United States"},{"startIP":"404619264","endIP":"404643839","countryCode":"US","countryName":"United States"},{"startIP":"404643840","endIP":"404652031","countryCode":"US","countryName":"United States"},{"startIP":"404652032","endIP":"404676607","countryCode":"US","countryName":"United States"},{"startIP":"404684800","endIP":"404692991","countryCode":"US","countryName":"United States"},{"startIP":"404692992","endIP":"404750335","countryCode":"US","countryName":"United States"},{"startIP":"404750336","endIP":"404815871","countryCode":"US","countryName":"United States"},{"startIP":"404815872","endIP":"404881407","countryCode":"US","countryName":"United States"},{"startIP":"404881408","endIP":"404946943","countryCode":"US","countryName":"United States"},{"startIP":"404946944","endIP":"404979711","countryCode":"US","countryName":"United States"},{"startIP":"404979712","endIP":"405012479","countryCode":"US","countryName":"United States"},{"startIP":"405012480","endIP":"405078015","countryCode":"CA","countryName":"Canada"},{"startIP":"405078016","endIP":"405143551","countryCode":"CA","countryName":"Canada"},{"startIP":"405143552","endIP":"405176319","countryCode":"US","countryName":"United States"},{"startIP":"405176320","endIP":"405180415","countryCode":"US","countryName":"United States"},{"startIP":"405180416","endIP":"405184511","countryCode":"CA","countryName":"Canada"},{"startIP":"405184512","endIP":"405192703","countryCode":"US","countryName":"United States"},{"startIP":"405192704","endIP":"405209087","countryCode":"US","countryName":"United States"},{"startIP":"405209088","endIP":"405274623","countryCode":"US","countryName":"United States"},{"startIP":"405274624","endIP":"405295103","countryCode":"US","countryName":"United States"},{"startIP":"405295104","endIP":"405299199","countryCode":"US","countryName":"United States"},{"startIP":"405299200","endIP":"405307391","countryCode":"US","countryName":"United States"},{"startIP":"405307392","endIP":"405331967","countryCode":"US","countryName":"United States"},{"startIP":"405331968","endIP":"405340159","countryCode":"US","countryName":"United States"},{"startIP":"405340160","endIP":"405364735","countryCode":"US","countryName":"United States"},{"startIP":"405372928","endIP":"405405695","countryCode":"PR","countryName":"Puerto Rico"},{"startIP":"405405696","endIP":"405422079","countryCode":"PR","countryName":"Puerto Rico"},{"startIP":"405422080","endIP":"405438463","countryCode":"US","countryName":"United States"},{"startIP":"405438464","endIP":"405471231","countryCode":"US","countryName":"United States"},{"startIP":"405471232","endIP":"405536767","countryCode":"US","countryName":"United States"},{"startIP":"405536768","endIP":"405798911","countryCode":"US","countryName":"United States"},{"startIP":"405798912","endIP":"405831679","countryCode":"CA","countryName":"Canada"},{"startIP":"405831680","endIP":"405839871","countryCode":"US","countryName":"United States"},{"startIP":"405839872","endIP":"405843967","countryCode":"US","countryName":"United States"},{"startIP":"405843968","endIP":"405848063","countryCode":"CA","countryName":"Canada"},{"startIP":"405848064","endIP":"405864447","countryCode":"PR","countryName":"Puerto Rico"},{"startIP":"405864448","endIP":"405872639","countryCode":"US","countryName":"United States"},{"startIP":"405872640","endIP":"405880831","countryCode":"US","countryName":"United States"},{"startIP":"405880832","endIP":"405889023","countryCode":"US","countryName":"United States"},{"startIP":"405889024","endIP":"405893119","countryCode":"US","countryName":"United States"},{"startIP":"405893120","endIP":"405897215","countryCode":"US","countryName":"United States"},{"startIP":"405897216","endIP":"405901311","countryCode":"US","countryName":"United States"},{"startIP":"405901312","endIP":"405905407","countryCode":"US","countryName":"United States"},{"startIP":"405905408","endIP":"405909503","countryCode":"US","countryName":"United States"},{"startIP":"405909504","endIP":"405917695","countryCode":"US","countryName":"United States"},{"startIP":"405917696","endIP":"405921791","countryCode":"US","countryName":"United States"},{"startIP":"405921792","endIP":"405929983","countryCode":"CA","countryName":"Canada"},{"startIP":"405929984","endIP":"405938175","countryCode":"US","countryName":"United States"},{"startIP":"405946368","endIP":"405962751","countryCode":"CA","countryName":"Canada"},{"startIP":"405962752","endIP":"405966847","countryCode":"US","countryName":"United States"},{"startIP":"405966848","endIP":"405970943","countryCode":"US","countryName":"United States"},{"startIP":"405979136","endIP":"405995519","countryCode":"PR","countryName":"Puerto Rico"},{"startIP":"406003712","endIP":"406011903","countryCode":"US","countryName":"United States"},{"startIP":"406011904","endIP":"406028287","countryCode":"BS","countryName":"Bahamas"},{"startIP":"406028288","endIP":"406044671","countryCode":"US","countryName":"United States"},{"startIP":"406044672","endIP":"406052863","countryCode":"US","countryName":"United States"},{"startIP":"406061056","endIP":"406064127","countryCode":"US","countryName":"United States"},{"startIP":"406064128","endIP":"406065663","countryCode":"US","countryName":"United States"},{"startIP":"406065664","endIP":"406067199","countryCode":"US","countryName":"United States"},{"startIP":"406067200","endIP":"406069247","countryCode":"US","countryName":"United States"},{"startIP":"406069248","endIP":"406070271","countryCode":"US","countryName":"United States"},{"startIP":"406070272","endIP":"406072319","countryCode":"US","countryName":"United States"},{"startIP":"406072320","endIP":"406074367","countryCode":"US","countryName":"United States"},{"startIP":"406074368","endIP":"406077439","countryCode":"US","countryName":"United States"},{"startIP":"406077440","endIP":"406093823","countryCode":"US","countryName":"United States"},{"startIP":"406093824","endIP":"406106111","countryCode":"US","countryName":"United States"},{"startIP":"406106112","endIP":"406110207","countryCode":"US","countryName":"United States"},{"startIP":"406110208","endIP":"406126591","countryCode":"CA","countryName":"Canada"},{"startIP":"406126592","endIP":"406142975","countryCode":"CA","countryName":"Canada"},{"startIP":"406142976","endIP":"406147071","countryCode":"US","countryName":"United States"},{"startIP":"406159360","endIP":"406175743","countryCode":"US","countryName":"United States"},{"startIP":"406183936","endIP":"406188031","countryCode":"CA","countryName":"Canada"},{"startIP":"406188032","endIP":"406192127","countryCode":"CA","countryName":"Canada"},{"startIP":"406192128","endIP":"406208511","countryCode":"CA","countryName":"Canada"},{"startIP":"406216704","endIP":"406224895","countryCode":"US","countryName":"United States"},{"startIP":"406224896","endIP":"406230527","countryCode":"US","countryName":"United States"},{"startIP":"406230528","endIP":"406232063","countryCode":"US","countryName":"United States"},{"startIP":"406232064","endIP":"406233087","countryCode":"US","countryName":"United States"},{"startIP":"406233088","endIP":"406234623","countryCode":"US","countryName":"United States"},{"startIP":"406234624","endIP":"406235135","countryCode":"US","countryName":"United States"},{"startIP":"406235136","endIP":"406236159","countryCode":"US","countryName":"United States"},{"startIP":"406236160","endIP":"406238207","countryCode":"US","countryName":"United States"},{"startIP":"406238208","endIP":"406241279","countryCode":"US","countryName":"United States"},{"startIP":"406241280","endIP":"406257663","countryCode":"PR","countryName":"Puerto Rico"},{"startIP":"406274048","endIP":"406290431","countryCode":"PR","countryName":"Puerto Rico"},{"startIP":"406298624","endIP":"406306815","countryCode":"PR","countryName":"Puerto Rico"},{"startIP":"406306816","endIP":"406323199","countryCode":"CA","countryName":"Canada"},{"startIP":"406323200","endIP":"406339583","countryCode":"US","countryName":"United States"},{"startIP":"406339584","endIP":"406347775","countryCode":"US","countryName":"United States"},{"startIP":"406347776","endIP":"406351871","countryCode":"US","countryName":"United States"},{"startIP":"406351872","endIP":"406355967","countryCode":"US","countryName":"United States"},{"startIP":"406355968","endIP":"406360063","countryCode":"US","countryName":"United States"},{"startIP":"406360064","endIP":"406362111","countryCode":"US","countryName":"United States"},{"startIP":"406362112","endIP":"406364159","countryCode":"US","countryName":"United States"},{"startIP":"406364160","endIP":"406365183","countryCode":"US","countryName":"United States"},{"startIP":"406365184","endIP":"406366207","countryCode":"US","countryName":"United States"},{"startIP":"406366208","endIP":"406366719","countryCode":"US","countryName":"United States"},{"startIP":"406366720","endIP":"406367231","countryCode":"US","countryName":"United States"},{"startIP":"406367232","endIP":"406368255","countryCode":"US","countryName":"United States"},{"startIP":"406368256","endIP":"406369791","countryCode":"US","countryName":"United States"},{"startIP":"406369792","endIP":"406370303","countryCode":"US","countryName":"United States"},{"startIP":"406370304","endIP":"406371327","countryCode":"US","countryName":"United States"},{"startIP":"406371328","endIP":"406371839","countryCode":"US","countryName":"United States"},{"startIP":"406371840","endIP":"406372351","countryCode":"US","countryName":"United States"},{"startIP":"406372352","endIP":"406388735","countryCode":"US","countryName":"United States"},{"startIP":"406388736","endIP":"406454271","countryCode":"CA","countryName":"Canada"},{"startIP":"406454272","endIP":"406585343","countryCode":"US","countryName":"United States"},{"startIP":"406585344","endIP":"406847487","countryCode":"US","countryName":"United States"},{"startIP":"406847488","endIP":"407371775","countryCode":"CA","countryName":"Canada"},{"startIP":"407371776","endIP":"407408639","countryCode":"CA","countryName":"Canada"},{"startIP":"407408640","endIP":"407412735","countryCode":"US","countryName":"United States"},{"startIP":"407412736","endIP":"407420927","countryCode":"US","countryName":"United States"},{"startIP":"407420928","endIP":"407429119","countryCode":"US","countryName":"United States"},{"startIP":"407429120","endIP":"407437311","countryCode":"US","countryName":"United States"},{"startIP":"407437312","endIP":"407502847","countryCode":"US","countryName":"United States"},{"startIP":"407502848","endIP":"407568383","countryCode":"US","countryName":"United States"},{"startIP":"407568384","endIP":"407597055","countryCode":"US","countryName":"United States"},{"startIP":"407597056","endIP":"407601151","countryCode":"US","countryName":"United States"},{"startIP":"407601152","endIP":"407605247","countryCode":"US","countryName":"United States"},{"startIP":"407609344","endIP":"407613439","countryCode":"US","countryName":"United States"},{"startIP":"407617536","endIP":"407619583","countryCode":"US","countryName":"United States"},{"startIP":"407619584","endIP":"407633919","countryCode":"US","countryName":"United States"},{"startIP":"407633920","endIP":"407896063","countryCode":"CA","countryName":"Canada"},{"startIP":"407896064","endIP":"408420351","countryCode":"CA","countryName":"Canada"},{"startIP":"408420352","endIP":"408485887","countryCode":"US","countryName":"United States"},{"startIP":"408485888","endIP":"408494079","countryCode":"US","countryName":"United States"},{"startIP":"408494080","endIP":"408502271","countryCode":"US","countryName":"United States"},{"startIP":"408502272","endIP":"408518655","countryCode":"CA","countryName":"Canada"},{"startIP":"408518656","endIP":"408535039","countryCode":"US","countryName":"United States"},{"startIP":"408535040","endIP":"408551423","countryCode":"CA","countryName":"Canada"},{"startIP":"408551424","endIP":"408616959","countryCode":"US","countryName":"United States"},{"startIP":"408616960","endIP":"408682495","countryCode":"US","countryName":"United States"},{"startIP":"408682496","endIP":"408719359","countryCode":"US","countryName":"United States"},{"startIP":"408719360","endIP":"408723455","countryCode":"VC","countryName":"Saint Vincent and the Grenadines"},{"startIP":"408723456","endIP":"408944639","countryCode":"US","countryName":"United States"},{"startIP":"408944640","endIP":"409010175","countryCode":"US","countryName":"United States"},{"startIP":"409010176","endIP":"409075711","countryCode":"US","countryName":"United States"},{"startIP":"409075712","endIP":"409206783","countryCode":"US","countryName":"United States"},{"startIP":"409206784","endIP":"409255935","countryCode":"US","countryName":"United States"},{"startIP":"409255936","endIP":"409272319","countryCode":"CA","countryName":"Canada"},{"startIP":"409272320","endIP":"409337855","countryCode":"US","countryName":"United States"},{"startIP":"409337856","endIP":"409354239","countryCode":"CA","countryName":"Canada"},{"startIP":"409370624","endIP":"409403391","countryCode":"US","countryName":"United States"},{"startIP":"409403392","endIP":"409468927","countryCode":"US","countryName":"United States"},{"startIP":"409468928","endIP":"409509887","countryCode":"US","countryName":"United States"},{"startIP":"409534464","endIP":"409550847","countryCode":"US","countryName":"United States"},{"startIP":"409567232","endIP":"409583615","countryCode":"US","countryName":"United States"},{"startIP":"409583616","endIP":"409591807","countryCode":"US","countryName":"United States"},{"startIP":"409591808","endIP":"409599999","countryCode":"US","countryName":"United States"},{"startIP":"409600000","endIP":"409616383","countryCode":"US","countryName":"United States"},{"startIP":"409616384","endIP":"409632767","countryCode":"US","countryName":"United States"},{"startIP":"409632768","endIP":"409665535","countryCode":"US","countryName":"United States"},{"startIP":"409665536","endIP":"409731071","countryCode":"US","countryName":"United States"},{"startIP":"409731072","endIP":"409862143","countryCode":"CA","countryName":"Canada"},{"startIP":"409862144","endIP":"409927679","countryCode":"US","countryName":"United States"},{"startIP":"409927680","endIP":"409993215","countryCode":"US","countryName":"United States"},{"startIP":"409993216","endIP":"410025983","countryCode":"US","countryName":"United States"},{"startIP":"410025984","endIP":"410058751","countryCode":"US","countryName":"United States"},{"startIP":"410058752","endIP":"410124287","countryCode":"US","countryName":"United States"},{"startIP":"410124288","endIP":"410157055","countryCode":"CA","countryName":"Canada"},{"startIP":"410157056","endIP":"410189823","countryCode":"CA","countryName":"Canada"},{"startIP":"410189824","endIP":"410255359","countryCode":"US","countryName":"United States"},{"startIP":"410255360","endIP":"410386431","countryCode":"US","countryName":"United States"},{"startIP":"410386432","endIP":"410451967","countryCode":"US","countryName":"United States"},{"startIP":"410451968","endIP":"410517503","countryCode":"US","countryName":"United States"},{"startIP":"410517504","endIP":"410583039","countryCode":"US","countryName":"United States"},{"startIP":"410583040","endIP":"410648575","countryCode":"US","countryName":"United States"},{"startIP":"410648576","endIP":"410714111","countryCode":"CA","countryName":"Canada"},{"startIP":"410714112","endIP":"410746879","countryCode":"US","countryName":"United States"},{"startIP":"410746880","endIP":"410779647","countryCode":"US","countryName":"United States"},{"startIP":"410779648","endIP":"410812415","countryCode":"US","countryName":"United States"},{"startIP":"410812416","endIP":"410845183","countryCode":"US","countryName":"United States"},{"startIP":"410845184","endIP":"410910719","countryCode":"US","countryName":"United States"},{"startIP":"410910720","endIP":"411041791","countryCode":"US","countryName":"United States"},{"startIP":"411041792","endIP":"411107327","countryCode":"US","countryName":"United States"},{"startIP":"411107328","endIP":"411140095","countryCode":"US","countryName":"United States"},{"startIP":"411140096","endIP":"411156479","countryCode":"US","countryName":"United States"},{"startIP":"411164672","endIP":"411168767","countryCode":"CA","countryName":"Canada"},{"startIP":"411172864","endIP":"411303935","countryCode":"US","countryName":"United States"},{"startIP":"411303936","endIP":"411336703","countryCode":"NL","countryName":"Netherlands"},{"startIP":"411336704","endIP":"411369471","countryCode":"NL","countryName":"Netherlands"},{"startIP":"411369472","endIP":"411435007","countryCode":"TR","countryName":"Turkey"},{"startIP":"411435008","endIP":"411500543","countryCode":"DE","countryName":"Germany"},{"startIP":"411500544","endIP":"411566079","countryCode":"RS","countryName":"Serbia"},{"startIP":"411566080","endIP":"411574271","countryCode":"US","countryName":"United States"},{"startIP":"411574272","endIP":"411582463","countryCode":"US","countryName":"United States"},{"startIP":"411582464","endIP":"411590655","countryCode":"US","countryName":"United States"},{"startIP":"411590656","endIP":"411598847","countryCode":"US","countryName":"United States"},{"startIP":"411598848","endIP":"411631615","countryCode":"US","countryName":"United States"},{"startIP":"411631616","endIP":"411639807","countryCode":"US","countryName":"United States"},{"startIP":"411639808","endIP":"411643903","countryCode":"CA","countryName":"Canada"},{"startIP":"411648000","endIP":"411664383","countryCode":"CA","countryName":"Canada"},{"startIP":"411664384","endIP":"411680767","countryCode":"US","countryName":"United States"},{"startIP":"411680768","endIP":"411688959","countryCode":"CA","countryName":"Canada"},{"startIP":"411688960","endIP":"411697151","countryCode":"PR","countryName":"Puerto Rico"},{"startIP":"411697152","endIP":"411717631","countryCode":"CA","countryName":"Canada"},{"startIP":"411721728","endIP":"411729919","countryCode":"CA","countryName":"Canada"},{"startIP":"411729920","endIP":"411746303","countryCode":"CA","countryName":"Canada"},{"startIP":"411746304","endIP":"411762687","countryCode":"PR","countryName":"Puerto Rico"},{"startIP":"411762688","endIP":"411770879","countryCode":"CA","countryName":"Canada"},{"startIP":"411770880","endIP":"411779071","countryCode":"US","countryName":"United States"},{"startIP":"411779072","endIP":"411795455","countryCode":"PR","countryName":"Puerto Rico"},{"startIP":"411795456","endIP":"411828223","countryCode":"PR","countryName":"Puerto Rico"},{"startIP":"411828224","endIP":"411885567","countryCode":"US","countryName":"United States"},{"startIP":"411893760","endIP":"411959295","countryCode":"CA","countryName":"Canada"},{"startIP":"411959296","endIP":"411975679","countryCode":"CA","countryName":"Canada"},{"startIP":"411975680","endIP":"411979775","countryCode":"US","countryName":"United States"},{"startIP":"411979776","endIP":"411983871","countryCode":"CA","countryName":"Canada"},{"startIP":"411983872","endIP":"411992063","countryCode":"US","countryName":"United States"},{"startIP":"411992064","endIP":"412024831","countryCode":"US","countryName":"United States"},{"startIP":"412024832","endIP":"412033023","countryCode":"US","countryName":"United States"},{"startIP":"412033024","endIP":"412041215","countryCode":"US","countryName":"United States"},{"startIP":"412041216","endIP":"412057599","countryCode":"US","countryName":"United States"},{"startIP":"412073984","endIP":"412082175","countryCode":"US","countryName":"United States"},{"startIP":"412082176","endIP":"412090367","countryCode":"US","countryName":"United States"},{"startIP":"412090368","endIP":"412106751","countryCode":"US","countryName":"United States"},{"startIP":"412106752","endIP":"412123135","countryCode":"US","countryName":"United States"},{"startIP":"412123136","endIP":"412155903","countryCode":"US","countryName":"United States"},{"startIP":"412155904","endIP":"412188671","countryCode":"US","countryName":"United States"},{"startIP":"412188672","endIP":"412221439","countryCode":"US","countryName":"United States"},{"startIP":"412221440","endIP":"412229631","countryCode":"CA","countryName":"Canada"},{"startIP":"412254208","endIP":"412286975","countryCode":"US","countryName":"United States"},{"startIP":"412286976","endIP":"412352511","countryCode":"US","countryName":"United States"},{"startIP":"412352512","endIP":"412377087","countryCode":"US","countryName":"United States"},{"startIP":"412377088","endIP":"412385279","countryCode":"US","countryName":"United States"},{"startIP":"412385280","endIP":"412418047","countryCode":"US","countryName":"United States"},{"startIP":"412418048","endIP":"412426239","countryCode":"US","countryName":"United States"},{"startIP":"412426240","endIP":"412434431","countryCode":"US","countryName":"United States"},{"startIP":"412434432","endIP":"412450815","countryCode":"US","countryName":"United States"},{"startIP":"412450816","endIP":"412483583","countryCode":"US","countryName":"United States"},{"startIP":"412483584","endIP":"412549119","countryCode":"CA","countryName":"Canada"},{"startIP":"412549120","endIP":"412614655","countryCode":"US","countryName":"United States"},{"startIP":"412647424","endIP":"412663807","countryCode":"US","countryName":"United States"},{"startIP":"412663808","endIP":"412680191","countryCode":"US","countryName":"United States"},{"startIP":"412680192","endIP":"412688383","countryCode":"CA","countryName":"Canada"},{"startIP":"412688384","endIP":"412696575","countryCode":"US","countryName":"United States"},{"startIP":"412696576","endIP":"412704767","countryCode":"US","countryName":"United States"},{"startIP":"412704768","endIP":"412708863","countryCode":"CA","countryName":"Canada"},{"startIP":"412708864","endIP":"412712959","countryCode":"US","countryName":"United States"},{"startIP":"412712960","endIP":"412745727","countryCode":"US","countryName":"United States"},{"startIP":"412745728","endIP":"412811263","countryCode":"US","countryName":"United States"},{"startIP":"412811264","endIP":"412876799","countryCode":"US","countryName":"United States"},{"startIP":"412876800","endIP":"412909567","countryCode":"US","countryName":"United States"},{"startIP":"412909568","endIP":"412917759","countryCode":"CA","countryName":"Canada"},{"startIP":"412925952","endIP":"412942335","countryCode":"CA","countryName":"Canada"},{"startIP":"412942336","endIP":"412946431","countryCode":"US","countryName":"United States"},{"startIP":"412946432","endIP":"412950527","countryCode":"PR","countryName":"Puerto Rico"},{"startIP":"412950528","endIP":"412958719","countryCode":"US","countryName":"United States"},{"startIP":"412975104","endIP":"413007871","countryCode":"CA","countryName":"Canada"},{"startIP":"413007872","endIP":"413073407","countryCode":"US","countryName":"United States"},{"startIP":"413073408","endIP":"413138943","countryCode":"US","countryName":"United States"},{"startIP":"413138944","endIP":"413827071","countryCode":"US","countryName":"United States"},{"startIP":"413827072","endIP":"413843455","countryCode":"US","countryName":"United States"},{"startIP":"413843456","endIP":"413847551","countryCode":"US","countryName":"United States"},{"startIP":"413847552","endIP":"413851647","countryCode":"US","countryName":"United States"},{"startIP":"413851648","endIP":"413859839","countryCode":"US","countryName":"United States"},{"startIP":"413859840","endIP":"413892607","countryCode":"US","countryName":"United States"},{"startIP":"413892608","endIP":"413900799","countryCode":"US","countryName":"United States"},{"startIP":"413900800","endIP":"413908991","countryCode":"US","countryName":"United States"},{"startIP":"413908992","endIP":"413925375","countryCode":"PR","countryName":"Puerto Rico"},{"startIP":"413925376","endIP":"413990911","countryCode":"US","countryName":"United States"},{"startIP":"413990912","endIP":"414056447","countryCode":"US","countryName":"United States"},{"startIP":"414056448","endIP":"414187519","countryCode":"US","countryName":"United States"},{"startIP":"414187520","endIP":"414711807","countryCode":"US","countryName":"United States"},{"startIP":"414711808","endIP":"414973951","countryCode":"US","countryName":"United States"},{"startIP":"414973952","endIP":"415236095","countryCode":"US","countryName":"United States"},{"startIP":"415236096","endIP":"415301631","countryCode":"US","countryName":"United States"},{"startIP":"415301632","endIP":"415367167","countryCode":"US","countryName":"United States"},{"startIP":"415367168","endIP":"415498239","countryCode":"US","countryName":"United States"},{"startIP":"415498240","endIP":"415629311","countryCode":"US","countryName":"United States"},{"startIP":"415629312","endIP":"415694847","countryCode":"US","countryName":"United States"},{"startIP":"415694848","endIP":"415711231","countryCode":"US","countryName":"United States"},{"startIP":"415711232","endIP":"415727615","countryCode":"US","countryName":"United States"},{"startIP":"415727616","endIP":"415760383","countryCode":"US","countryName":"United States"},{"startIP":"415760384","endIP":"416022527","countryCode":"CA","countryName":"Canada"},{"startIP":"416022528","endIP":"416059391","countryCode":"US","countryName":"United States"},{"startIP":"416059392","endIP":"416063487","countryCode":"CA","countryName":"Canada"},{"startIP":"416071680","endIP":"416088063","countryCode":"CA","countryName":"Canada"},{"startIP":"416088064","endIP":"416153599","countryCode":"US","countryName":"United States"},{"startIP":"416153600","endIP":"416161791","countryCode":"BS","countryName":"Bahamas"},{"startIP":"416161792","endIP":"416169983","countryCode":"US","countryName":"United States"},{"startIP":"416169984","endIP":"416186367","countryCode":"US","countryName":"United States"},{"startIP":"416186368","endIP":"416219135","countryCode":"US","countryName":"United States"},{"startIP":"416219136","endIP":"416251903","countryCode":"CA","countryName":"Canada"},{"startIP":"416251904","endIP":"416284671","countryCode":"US","countryName":"United States"},{"startIP":"416284672","endIP":"416546815","countryCode":"US","countryName":"United States"},{"startIP":"416546816","endIP":"416579583","countryCode":"CA","countryName":"Canada"},{"startIP":"416579584","endIP":"416612351","countryCode":"CA","countryName":"Canada"},{"startIP":"416612352","endIP":"416628735","countryCode":"US","countryName":"United States"},{"startIP":"416628736","endIP":"416636927","countryCode":"CA","countryName":"Canada"},{"startIP":"416636928","endIP":"416641023","countryCode":"US","countryName":"United States"},{"startIP":"416641024","endIP":"416645119","countryCode":"US","countryName":"United States"},{"startIP":"416645120","endIP":"416677887","countryCode":"US","countryName":"United States"},{"startIP":"416677888","endIP":"416743423","countryCode":"US","countryName":"United States"},{"startIP":"416743424","endIP":"416759807","countryCode":"CA","countryName":"Canada"},{"startIP":"416759808","endIP":"416776191","countryCode":"CA","countryName":"Canada"},{"startIP":"416776192","endIP":"416808959","countryCode":"US","countryName":"United States"},{"startIP":"416808960","endIP":"416874495","countryCode":"US","countryName":"United States"},{"startIP":"416874496","endIP":"416940031","countryCode":"US","countryName":"United States"},{"startIP":"416940032","endIP":"417005567","countryCode":"US","countryName":"United States"},{"startIP":"417005568","endIP":"417071103","countryCode":"US","countryName":"United States"},{"startIP":"417071104","endIP":"417136639","countryCode":"US","countryName":"United States"},{"startIP":"417136640","endIP":"417202175","countryCode":"US","countryName":"United States"},{"startIP":"417202176","endIP":"417267711","countryCode":"CA","countryName":"Canada"},{"startIP":"417267712","endIP":"417288191","countryCode":"US","countryName":"United States"},{"startIP":"417288192","endIP":"417292287","countryCode":"US","countryName":"United States"},{"startIP":"417292288","endIP":"417300479","countryCode":"US","countryName":"United States"},{"startIP":"417300480","endIP":"417333247","countryCode":"US","countryName":"United States"},{"startIP":"417333248","endIP":"417341439","countryCode":"US","countryName":"United States"},{"startIP":"417341440","endIP":"417349631","countryCode":"US","countryName":"United States"},{"startIP":"417349632","endIP":"417366015","countryCode":"US","countryName":"United States"},{"startIP":"417366016","endIP":"417398783","countryCode":"CA","countryName":"Canada"},{"startIP":"417398784","endIP":"417406975","countryCode":"US","countryName":"United States"},{"startIP":"417406976","endIP":"417423359","countryCode":"US","countryName":"United States"},{"startIP":"417423360","endIP":"417427455","countryCode":"US","countryName":"United States"},{"startIP":"417427456","endIP":"417431551","countryCode":"US","countryName":"United States"},{"startIP":"417431552","endIP":"417464319","countryCode":"CA","countryName":"Canada"},{"startIP":"417464320","endIP":"417497087","countryCode":"CA","countryName":"Canada"},{"startIP":"417497088","endIP":"417529855","countryCode":"CA","countryName":"Canada"},{"startIP":"417529856","endIP":"417538047","countryCode":"PR","countryName":"Puerto Rico"},{"startIP":"417538048","endIP":"417595391","countryCode":"US","countryName":"United States"},{"startIP":"417595392","endIP":"417660927","countryCode":"US","countryName":"United States"},{"startIP":"417660928","endIP":"417726463","countryCode":"US","countryName":"United States"},{"startIP":"417726464","endIP":"417734655","countryCode":"US","countryName":"United States"},{"startIP":"417734656","endIP":"417775615","countryCode":"US","countryName":"United States"},{"startIP":"417775616","endIP":"417791999","countryCode":"CA","countryName":"Canada"},{"startIP":"417792000","endIP":"417796095","countryCode":"CA","countryName":"Canada"},{"startIP":"417796096","endIP":"417800191","countryCode":"US","countryName":"United States"},{"startIP":"417800192","endIP":"417808383","countryCode":"BS","countryName":"Bahamas"},{"startIP":"417808384","endIP":"417816575","countryCode":"CA","countryName":"Canada"},{"startIP":"417816576","endIP":"417820671","countryCode":"CA","countryName":"Canada"},{"startIP":"417820672","endIP":"417824767","countryCode":"US","countryName":"United States"},{"startIP":"417824768","endIP":"417857535","countryCode":"US","countryName":"United States"},{"startIP":"417857536","endIP":"417923071","countryCode":"AR","countryName":"Argentina"},{"startIP":"417923072","endIP":"417931263","countryCode":"US","countryName":"United States"},{"startIP":"417931264","endIP":"417939455","countryCode":"US","countryName":"United States"},{"startIP":"417939456","endIP":"417947647","countryCode":"US","countryName":"United States"},{"startIP":"417947648","endIP":"417955839","countryCode":"US","countryName":"United States"},{"startIP":"417955840","endIP":"417964031","countryCode":"US","countryName":"United States"},{"startIP":"417964032","endIP":"417972223","countryCode":"US","countryName":"United States"},{"startIP":"417972224","endIP":"417988607","countryCode":"US","countryName":"United States"},{"startIP":"417988608","endIP":"418054143","countryCode":"US","countryName":"United States"},{"startIP":"418054144","endIP":"418062335","countryCode":"US","countryName":"United States"},{"startIP":"418062336","endIP":"418070527","countryCode":"CA","countryName":"Canada"},{"startIP":"418070528","endIP":"418074623","countryCode":"US","countryName":"United States"},{"startIP":"418074624","endIP":"418078719","countryCode":"US","countryName":"United States"},{"startIP":"418078720","endIP":"418086911","countryCode":"CA","countryName":"Canada"},{"startIP":"418086912","endIP":"418119679","countryCode":"CA","countryName":"Canada"},{"startIP":"418119680","endIP":"418127871","countryCode":"US","countryName":"United States"},{"startIP":"418127872","endIP":"418129919","countryCode":"US","countryName":"United States"},{"startIP":"418129920","endIP":"418131967","countryCode":"US","countryName":"United States"},{"startIP":"418131968","endIP":"418132991","countryCode":"US","countryName":"United States"},{"startIP":"418132992","endIP":"418134015","countryCode":"US","countryName":"United States"},{"startIP":"418134016","endIP":"418135039","countryCode":"US","countryName":"United States"},{"startIP":"418135040","endIP":"418136063","countryCode":"US","countryName":"United States"},{"startIP":"418136064","endIP":"418152447","countryCode":"US","countryName":"United States"},{"startIP":"418152448","endIP":"418185215","countryCode":"US","countryName":"United States"},{"startIP":"418185216","endIP":"418250751","countryCode":"US","countryName":"United States"},{"startIP":"418250752","endIP":"418258943","countryCode":"US","countryName":"United States"},{"startIP":"418258944","endIP":"418275327","countryCode":"US","countryName":"United States"},{"startIP":"418275328","endIP":"418283519","countryCode":"US","countryName":"United States"},{"startIP":"418283520","endIP":"418316287","countryCode":"US","countryName":"United States"},{"startIP":"418316288","endIP":"418320383","countryCode":"CA","countryName":"Canada"},{"startIP":"418320384","endIP":"418324479","countryCode":"US","countryName":"United States"},{"startIP":"418324480","endIP":"418332671","countryCode":"US","countryName":"United States"},{"startIP":"418332672","endIP":"418349055","countryCode":"US","countryName":"United States"},{"startIP":"418349056","endIP":"418365439","countryCode":"US","countryName":"United States"},{"startIP":"418365440","endIP":"418381823","countryCode":"US","countryName":"United States"},{"startIP":"418381824","endIP":"418512895","countryCode":"US","countryName":"United States"},{"startIP":"418512896","endIP":"418643967","countryCode":"US","countryName":"United States"},{"startIP":"418643968","endIP":"418660351","countryCode":"CA","countryName":"Canada"},{"startIP":"418660352","endIP":"418664447","countryCode":"CA","countryName":"Canada"},{"startIP":"418664448","endIP":"418668543","countryCode":"CA","countryName":"Canada"},{"startIP":"418668544","endIP":"418672639","countryCode":"US","countryName":"United States"},{"startIP":"418672640","endIP":"418676735","countryCode":"CA","countryName":"Canada"},{"startIP":"418676736","endIP":"418693119","countryCode":"BS","countryName":"Bahamas"},{"startIP":"418693120","endIP":"418709503","countryCode":"CA","countryName":"Canada"},{"startIP":"418709504","endIP":"418725887","countryCode":"US","countryName":"United States"},{"startIP":"418725888","endIP":"418729983","countryCode":"US","countryName":"United States"},{"startIP":"418729984","endIP":"418734079","countryCode":"US","countryName":"United States"},{"startIP":"418734080","endIP":"418742271","countryCode":"US","countryName":"United States"},{"startIP":"418742272","endIP":"418766847","countryCode":"US","countryName":"United States"},{"startIP":"418766848","endIP":"418770943","countryCode":"CA","countryName":"Canada"},{"startIP":"418770944","endIP":"418775039","countryCode":"US","countryName":"United States"},{"startIP":"418775040","endIP":"418799615","countryCode":"CA","countryName":"Canada"},{"startIP":"418799616","endIP":"418807807","countryCode":"US","countryName":"United States"},{"startIP":"418807808","endIP":"418824191","countryCode":"US","countryName":"United States"},{"startIP":"418824192","endIP":"418832383","countryCode":"US","countryName":"United States"},{"startIP":"418832384","endIP":"418840575","countryCode":"US","countryName":"United States"},{"startIP":"418840576","endIP":"418906111","countryCode":"US","countryName":"United States"},{"startIP":"418906112","endIP":"419430399","countryCode":"US","countryName":"United States"},{"startIP":"419430400","endIP":"436207615","countryCode":"GB","countryName":"Great Britain (UK)"}]